{
  "actions": [
    "MoveTo|-0.32, -299.98, 30.21|",

    "MoveTo|46.56, -299.98, -29.28|",

    "StopForCombat|39.41, -300.00, -29.02|False",
    "MoveTo|2.66, -299.98, -29.87|",
    "Wait|0, 0, 0|2200",
    "StopForCombat|-8.70, -300.00, -29.66|True",

    "MoveTo|-0.07, -300.00, -36.51|",
    "MoveTo|-1.03, -299.98, -63.97|",
    "MoveTo|-34.40, -300.00, -81.15|",

    "MoveTo|-17.80, -291.96, -98.11|",
    "UnsyncedMoveTo|-15.96, -291.96, -89.27|",
    "Boss|8.32, -291.95, -99.99|",

    "StopForCombat|8.13, -282.35, -151.39|False",
    "MoveTo|51.59, -263.98, -79.44|",
    "Wait|0, 0, 0|2200",
    "TreasureCoffer|76.00, -263.98, -31.58|",
    "StopForCombat|52.59, -263.98, 1.49|True",

    "StopForCombat|62.00, -263.98, 24.08|False",
    "MoveTo|89.92, -263.98, 3.35|",
    "TreasureCoffer|68.14, -263.98, -14.68|",
    "StopForCombat|85.91, -263.98, -1.18|True",

    "MoveTo|103.88, -263.87, -0.01|",
    "AutoMoveFor|105.43, -263.87, 0.03|3000",
    "Wait|0, 0, 0|1000",

    "StopForCombat|0, 0, 0|False",
    "MoveTo|61.01, 0.00, 51.35|",
    "Wait|0, 0, 0|4200",
    "StopForCombat|24.61, 0.00, 72.32|True",

    "MoveTo|17.66, 0.00, 72.04|",
    "UnsyncedMoveTo|16.22, 0.00, 61.81|",
    "Boss|-5.85, 0.00, 72.00|",

    "StopForCombat|0, 0, 0|False",
    "MoveTo|-60.08, -0.00, 34.96|",
    "Wait|0, 0, 0|2200",
    "MoveTo|-76.64, 0.00, 27.61|",
    "Wait|0, 0, 0|2200",
    "MoveTo|-92.53, 0.00, 6.05|",
    "Wait|0, 0, 0|1200",
    "StopForCombat|-98.11, 0.00, 3.96|True",

    "TreasureCoffer|-78.27, 0.00, -15.41|",
    "MoveTo|-108.95, 0.00, -0.07|",
    "AutoMoveFor|-111.48, 0.13, -0.04|3000",
    "Wait|0, 0, 0|1000",

    "StopForCombat|0, 0, 0|False",
    "TreasureCoffer|-59.72, 285.00, -18.08|",
    "MoveTo|-60.17, 291.00, 25.12|",
    "Wait|0, 0, 0|4200",
    "StopForCombat|-60.23, 291.00, 53.64|True",

    "Boss|0.11, 300.00, -6.84|"
  ],
  "meta": {
    "createdAt": 136,
    "changelog": [],
    "notes": []
  }
}